jaws_scripts/__init__.py
jaws_scripts/broker/__init__.py
jaws_scripts/broker/create_topics.py
jaws_scripts/broker/delete_topics.py
jaws_scripts/broker/describe_topics.py
jaws_scripts/broker/list_topics.py
jaws_scripts/broker/show_consumer_groups.py
jaws_scripts/client/__init__.py
jaws_scripts/client/list_activations.py
jaws_scripts/client/list_categories.py
jaws_scripts/client/list_classes.py
jaws_scripts/client/list_effective_alarms.py
jaws_scripts/client/list_effective_notifications.py
jaws_scripts/client/list_effective_registrations.py
jaws_scripts/client/list_instances.py
jaws_scripts/client/list_locations.py
jaws_scripts/client/list_overrides.py
jaws_scripts/client/set_activation.py
jaws_scripts/client/set_category.py
jaws_scripts/client/set_class.py
jaws_scripts/client/set_effective_alarm.py
jaws_scripts/client/set_effective_notification.py
jaws_scripts/client/set_effective_registration.py
jaws_scripts/client/set_instance.py
jaws_scripts/client/set_location.py
jaws_scripts/client/set_override.py
jaws_scripts/registry/__init__.py
jaws_scripts/registry/create_schemas.py
jaws_scripts/registry/delete_schemas.py
jaws_scripts/registry/describe_schemas.py
jaws_scripts/registry/describe_version.py
jaws_scripts/registry/list_schemas.py
jaws_scripts-4.5.4.dist-info/LICENSE
jaws_scripts-4.5.4.dist-info/METADATA
jaws_scripts-4.5.4.dist-info/WHEEL
jaws_scripts-4.5.4.dist-info/entry_points.txt
jaws_scripts-4.5.4.dist-info/top_level.txt
jaws_scripts-4.5.4.dist-info/RECORD
