Metadata-Version: 2.1
Name: jaws-scripts
Version: 4.5.4
Summary: JLab Alarm Warning System (JAWS) Admin Scripts
Home-page: https://github.com/JeffersonLab/jaws
Author: Ryan Slominski
Author-email: ryans@jlab.org
Project-URL: Bug Tracker, https://github.com/JeffersonLab/jaws/issues
Classifier: Programming Language :: Python :: 3
Classifier: License :: OSI Approved :: MIT License
Classifier: Operating System :: OS Independent
Requires-Python: >=3.9
License-File: LICENSE
Requires-Dist: jaws-libp (==4.4.1)
Requires-Dist: click (>=7.1.2)
Provides-Extra: dev
Requires-Dist: build (>=0.8.0) ; extra == 'dev'
Requires-Dist: pytest (>=7.1.2) ; extra == 'dev'
Requires-Dist: pylint (>=2.14.4) ; extra == 'dev'
Requires-Dist: Sphinx (>=5.0.2) ; extra == 'dev'
Requires-Dist: sphinx-click (>=4.3.0) ; extra == 'dev'
Requires-Dist: sphinx-rtd-theme (>=1.0.0) ; extra == 'dev'
